smtp_tool/__init__.py
smtp_tool/email_sender.py
smtp_tool/smtp_config.py
smtp_tool-0.2.0.dist-info/METADATA
smtp_tool-0.2.0.dist-info/WHEEL
smtp_tool-0.2.0.dist-info/top_level.txt
smtp_tool-0.2.0.dist-info/RECORD
