Metadata-Version: 2.4
Name: smtp_tool
Version: 0.2.0
Summary: Simple SMTP email sending utility
Author-email: LazyKitty <wenzhao5105@163.com>
Project-URL: Homepage, https://pypi.org/project/smtp_tool/
Project-URL: Repository, https://github.com/lazylemoncat/smtp_tool
Keywords: smtp,email
Classifier: Programming Language :: Python :: 3
Classifier: License :: OSI Approved :: MIT License
Classifier: Operating System :: OS Independent
Classifier: Topic :: Communications :: Email
Requires-Python: >=3.8
